{
  "entryFile": "src/app.ts",
  "noImplicitAdditionalProperties": "throw-on-extras",
  "controllerPathGlobs": ["src/controllers/**/*Controller.ts"],
  "spec": {
    "outputDirectory": "docs",
    "specVersion": 3,
    "name": "Markdown Notes API",
    "description": "RESTful API for managing markdown notes with grammar checking",
    "version": "1.0.0",
    "license": "ISC",
    "contact": {
      "name": "API Support",
      "email": "support@example.com"
    },
    "schemes": ["http"],
    "host": "localhost:3000",
    "basePath": "/"
  },
  "routes": {
    "routesDir": "src/routes"
  }
}
